steve/video_reqs.json
steve/util.py
steve/__init__.py
steve/richardapi.py
steve/cmdline.py
steve/restapi.py
steve/webedit.py
steve/templates/home.html
steve/templates/base.html
steve/templates/edit.html
steve/tests/test_utils.py
steve/tests/__init__.py
steve/tests/test_restapi.py
steve-0.4.data/scripts/steve-cmd
steve-0.4.dist-info/WHEEL
steve-0.4.dist-info/top_level.txt
steve-0.4.dist-info/RECORD
steve-0.4.dist-info/METADATA
steve-0.4.dist-info/zip-safe
steve-0.4.dist-info/metadata.json
steve-0.4.dist-info/DESCRIPTION.rst
