Metadata-Version: 2.0
Name: steve
Version: 0.4
Summary: Command line importer for richard
Home-page: http://github.com/willkg/steve
Author: Will Kahn-Greene
Author-email: willg@bluesock.org
License: Simplified BSD License
Keywords: richard videos importer
Platform: UNKNOWN
Classifier: Development Status :: 5 - Production/Stable
Classifier: Environment :: Console
Classifier: License :: OSI Approved :: BSD License
Classifier: Operating System :: POSIX :: Linux
Classifier: Programming Language :: Python
Classifier: Programming Language :: Python :: 2.6
Classifier: Programming Language :: Python :: 2.7
Requires-Dist: argparse
Requires-Dist: blessings
Requires-Dist: cssselect
Requires-Dist: html2text
Requires-Dist: jinja2
Requires-Dist: nose
Requires-Dist: vidscraper
